{"maps":[{"name":"Academy","band":"Mutewind","dots":"2","reports_on_710":"2","last_report_text":"[1438282181] #ShannaBananaAwakes: academy hunters"},{"name":"Arachnid_Nest","band":"Mutewind","dots":"2","reports_on_710":"6","last_report_text":"[1438280247] #Botchli: arachnid nest: mutewind hunters"},{"name":"Arena","band":"Redblade","dots":"2","reports_on_710":"4","last_report_text":"[1438277964] #ZeeQaunn: arena raiders"},{"name":"Arsenal","band":"Mutewind","dots":"2","reports_on_710":"2","last_report_text":"[1438279385] #FoxTactics: Arsenal Mutewind Hunters"},{"name":"Bazaar","band":"Brinerot","dots":"3","reports_on_710":"1","last_report_text":"[1438278546] #IceCrashJxnz: bazaar brinerot buccaneers"},{"name":"Cells","band":"Redblade","dots":"1","reports_on_710":"6","last_report_text":"[1438281629] #WhisperingDream: cells redblade scouts"},{"name":"Cemetery","band":"Redblade","dots":"1","reports_on_710":"4","last_report_text":"[1438278382] #LemmiwinksWB: cemetary redblade scouts"},{"name":"Channel","band":"Redblade","dots":"2","reports_on_710":"4","last_report_text":"[1438278111] #LemmiwinksWB: channel Redblade Raiders"},{"name":"Colonnade","band":"Brinerot","dots":"2","reports_on_710":"6","last_report_text":"[1438278563] #Jeccu: colonnade pillagers"},{"name":"Coves","band":"Brinerot","dots":"3","reports_on_710":"2","last_report_text":"[1438277525] #NullUhrDreiundfuenfzig: coves brinerot buccaneers"},{"name":"Crypt","band":"Brinerot","dots":"2","reports_on_710":"2","last_report_text":"[1438277220] #Tywin_Lannister: crypt brinerot pillagers"},{"name":"Dark_Forest","band":"Brinerot","dots":"1","reports_on_710":"4","last_report_text":"[1438278176] #Oot: dark forest lookouts"},{"name":"Dry_Peninsula","band":"Redblade","dots":"1","reports_on_710":"2","last_report_text":"[1438277409] #BilboBaggins: dry peninsula scouts"},{"name":"Dry_Woods","band":"Mutewind","dots":"1","reports_on_710":"4","last_report_text":"[1438278193] #Myaesermint: dry woods mutewind trackers"},{"name":"Dungeon","band":"Redblade","dots":"2","reports_on_710":"2","last_report_text":"[1438276981] #Natch: dungeon redblade raiders"},{"name":"Gorge","band":"Brinerot","dots":"2","reports_on_710":"4","last_report_text":"[1438277810] #PaviPaviPaviPaviPavi: Gorge brinerot pillagers"},{"name":"Graveyard","band":"Mutewind","dots":"2","reports_on_710":"4","last_report_text":"[1438278302] #ElementaryMyDearVyld: Graveyard mutewind hunters"},{"name":"Jungle_Valley","band":"Brinerot","dots":"1","reports_on_710":"6","last_report_text":"[1438278945] #Rapta: jungle valle brinerot lookouts"},{"name":"Labyrinth","band":"Brinerot","dots":"1","reports_on_710":"2","last_report_text":"[1438278208] #Althasandria: Labyrinth - Brinerot Lookouts"},{"name":"Mountain_Ledge","band":"Brinerot","dots":"1","reports_on_710":"6","last_report_text":"[1438279549] #ButtockJuices: mountain ledge lookouts"},{"name":"Mud_Geyser","band":"Redblade","dots":"2","reports_on_710":"2","last_report_text":"[1438276927] #WBP: mud geyser redblade raiders"},{"name":"Necropolis","band":"Mutewind","dots":"1","reports_on_710":"4","last_report_text":"[1438279514] #ItalianHell: necropolis mutewind trackers"},{"name":"Olmec's_Sanctum","band":"Mutewind","dots":"3","reports_on_710":"4","last_report_text":"[1438277986] #LetsFindSomeShinyStuff: Olmec's Sanctum - Mutewind Purifiers"},{"name":"Orchard","band":"Brinerot","dots":"2","reports_on_710":"4","last_report_text":"[1438277502] #ShowMeYourDips: orchard pillagers"},{"name":"Overgrown_Shrine","band":"Brinerot","dots":"2","reports_on_710":"6","last_report_text":"[1438278639] #ButtockJuices: overgrown shrine brinerot pillagers"},{"name":"Pit","band":"Redblade","dots":"2","reports_on_710":"4","last_report_text":"[1438277443] #Chazy_D: Pit - Redblade raiders"},{"name":"Plateau","band":"Brinerot","dots":"2","reports_on_710":"1","last_report_text":"[1438281819] #Rapta: plateau brinerot pillagers"},{"name":"Poorjoy's_Asylum","band":"Brinerot","dots":"3","reports_on_710":"2","last_report_text":"[1438277170] #FoxTactics: Poorjoy's asylum brinerot buccaneers"},{"name":"Promenade","band":"Redblade","dots":"1","reports_on_710":"2","last_report_text":"[1438277353] #Hevi: promenade scouts"},{"name":"Quarry","band":"Mutewind","dots":"2","reports_on_710":"2","last_report_text":"[1438278231] #Neanderthal: quarry mutewind hunters"},{"name":"Residence","band":"Redblade","dots":"2","reports_on_710":"4","last_report_text":"[1438278070] #Spiral: Raiders Residence"},{"name":"Sewer","band":"Brinerot","dots":"1","reports_on_710":"4","last_report_text":"[1438277741] #CrashingFrozenSkulls: Sewer Lookouts"},{"name":"Shipyard","band":"Redblade","dots":"1","reports_on_710":"3","last_report_text":"[1438278856] #KrumpunaTomata: Redblade scouts in shipyard (71; Zana)"},{"name":"Spider_Forest","band":"Mutewind","dots":"1","reports_on_710":"4","last_report_text":"[1438277787] #BoomjooseWB: spider forest mutewind trackers"},{"name":"Spider_Lair","band":"Redblade","dots":"1","reports_on_710":"2","last_report_text":"[1438277089] #BoomjooseWB: spider lair redblade scouts"},{"name":"Temple","band":"Mutewind","dots":"2","reports_on_710":"2","last_report_text":"[1438276959] #Notsurewhatbuild: temple mutewind hunters"},{"name":"Torture_Chamber","band":"Mutewind","dots":"1","reports_on_710":"3","last_report_text":"[1438278461] #RIP_Stannis_Baratheon: torture chamber mutewind trackers"},{"name":"Tunnel","band":"Brinerot","dots":"1","reports_on_710":"1","last_report_text":"[1438282313] #SeibaThrower: tunnel brinerot lookouts"},{"name":"Underground_River","band":"Mutewind","dots":"2","reports_on_710":"2","last_report_text":"[1438276838] #PaviPaviPaviPaviPavi: Underground River mutewind hunters"},{"name":"Underground_Sea","band":"Redblade","dots":"1","reports_on_710":"4","last_report_text":"[1438277723] #ukigoboom: underground sea redblade scouts"},{"name":"Vaal_Pyramid","band":"Mutewind","dots":"1","reports_on_710":"4","last_report_text":"[1438277866] #ButtockJuices: vaal pyramid Mutewind Trackers"},{"name":"Villa","band":"Mutewind","dots":"1","reports_on_710":"4","last_report_text":"[1438278143] #FlavorOfTheMonthBuild: villa mutewind trackers"},{"name":"Village_Ruin","band":"Mutewind","dots":"1","reports_on_710":"2","last_report_text":"[1438278500] #FoxTactics: Village Ruin Mutewind Trackers"},{"name":"Volcano","band":"Redblade","dots":"1","reports_on_710":"2","last_report_text":"[1438278263] #PaviPaviPaviPaviPavi: volcano redblade scouts"},{"name":"Waste_Pool","band":"Mutewind","dots":"1","reports_on_710":"4","last_report_text":"[1438278629] #Lurker: Waste pool trackers"},{"name":"Waterways","band":"Mutewind","dots":"4","reports_on_710":"2","last_report_text":"[1438282754] #Doedre_The_Hutt: waterways cleansed"},{"name":"Whakawairua_Tuahu","band":"Brinerot","dots":"4","reports_on_710":"2","last_report_text":"[1438282443] #Sneaky_cyc: wakawairua tuahu is caputred by the brinerot"}],"timeslot":399521}