{"maps":[{"name":"Academy","band":"Brinerot","dots":"2","reports_on_710":"2","last_report_text":"[1438045147] #IyvaDC: Academy Brinerot Pillager"},{"name":"Arachnid_Nest","band":"Brinerot","dots":"1","reports_on_710":"2","last_report_text":"[1438044729] #BigOLCooookie: arachnid nest brinerot lookout"},{"name":"Arid_Lake","band":"Mutewind","dots":"1","reports_on_710":"2","last_report_text":"[1438044853] #LongDongLover: arid lake mutewind tracker"},{"name":"Bazaar","band":"Mutewind","dots":"3","reports_on_710":"2","last_report_text":"[1438044251] #RespectingAllTheBros: Bazaar Mutewind Purifier"},{"name":"Canyon","band":"Mutewind","dots":"2","reports_on_710":"2","last_report_text":"[1438043204] #Teldiarrow: canyon mutewind hunter"},{"name":"Catacomb","band":"Brinerot","dots":"1","reports_on_710":"2","last_report_text":"[1438043152] #Rubicant_Pois: catacombs Brinerot lookout"},{"name":"Colonnade","band":"Brinerot","dots":"1","reports_on_710":"2","last_report_text":"[1438043574] #ProPatriaX: Colonnade :: Brinerot Lookout"},{"name":"Coves","band":"Brinerot","dots":"2","reports_on_710":"2","last_report_text":"[1438043944] #Blem: coves brinerot pillager"},{"name":"Crematorium","band":"Mutewind","dots":"3","reports_on_710":"2","last_report_text":"[1438044894] #Selvian_Bows: crematorium = mutewind purifier"},{"name":"Desert","band":"Mutewind","dots":"2","reports_on_710":"2","last_report_text":"[1438044486] #Breaking_Ice: desert mutewind hunter"},{"name":"Dungeon","band":"Mutewind","dots":"3","reports_on_710":"2","last_report_text":"[1438045686] #Oot: dungeon mutewind purifier"},{"name":"Ghetto","band":"Redblade","dots":"3","reports_on_710":"2","last_report_text":"[1438044358] #NeedleSprayer: ghetto fanatic"},{"name":"Labyrinth","band":"Mutewind","dots":"3","reports_on_710":"2","last_report_text":"[1438043494] #Friggs: labyrinth mutewind purifier"},{"name":"Mud_Geyser","band":"Redblade","dots":"2","reports_on_710":"2","last_report_text":"[1438045733] #Rubicant_Pois: mud geyser redblade raider"},{"name":"Museum","band":"Brinerot","dots":"2","reports_on_710":"2","last_report_text":"[1438046028] #John_Frusciante: Museum Brinerot Pillager"},{"name":"Necropolis","band":"Mutewind","dots":"2","reports_on_710":"2","last_report_text":"[1438045683] #Breaking_Ice: necropolis zana mutewind hunter"},{"name":"Orchard","band":"Mutewind","dots":"2","reports_on_710":"2","last_report_text":"[1438044479] #ShadowedSkies:  Orchard - Mutewind Hunter"},{"name":"Promenade","band":"Redblade","dots":"1","reports_on_710":"2","last_report_text":"[1438043894] #SweepSweepSweepadelphia: Promenade Redblade Scout"},{"name":"Residence","band":"Brinerot","dots":"2","reports_on_710":"2","last_report_text":"[1438045392] #EPS_MeleeMarce: residence B"},{"name":"Sewer","band":"Redblade","dots":"4","reports_on_710":"4","last_report_text":"[1438043394] #RIP_Stannis_Baratheon: sewer conquered redblad"},{"name":"Shipyard","band":"Mutewind","dots":"4","reports_on_710":"4","last_report_text":"[1438044021] #RIP_Stannis_Baratheon: ya shipyard cleanse"},{"name":"Spider_Forest","band":"Brinerot","dots":"3","reports_on_710":"2","last_report_text":"[1438046117] #SweepSweepSweepadelphia: Spider Forest Brinerot Buccaneer"},{"name":"The_Apex_of_Sacrifice","band":"Redblade","dots":"3","reports_on_710":"2","last_report_text":"[1438043267] #RED_JACKET_BRO: The Apex of Sacrifice Redblade Fanatic"},{"name":"Thicket","band":"Mutewind","dots":"1","reports_on_710":"2","last_report_text":"[1438045403] #Reaving_Ranger: Thicket Mutewind Tracker"},{"name":"Torture_Chamber","band":"Brinerot","dots":"2","reports_on_710":"2","last_report_text":"[1438043419] #GreaseInMyEyes: torture chamber brinerot pillager"},{"name":"Underground_Sea","band":"Redblade","dots":"1","reports_on_710":"2","last_report_text":"[1438043202] #JustWannaHaveFun: Underground Sea Redblade Scout"},{"name":"Vaults_of_Atziri","band":"Brinerot","dots":"3","reports_on_710":"2","last_report_text":"[1438043189] #BulokuChansu: Vaults of Atziri = Buccaneer"},{"name":"Villa","band":"Redblade","dots":"3","reports_on_710":"2","last_report_text":"[1438044959] #ProPatriaX: Villa :: 3dot Redblade Fanatic"},{"name":"Waste_Pool","band":"Mutewind","dots":"1","reports_on_710":"2","last_report_text":"[1438043789] #RespectingAllTheBros: Waste Pool Mutewind Tracker"}],"timeslot":399456}