{"maps":[{"name":"Arachnid_Nest","band":"Mutewind","dots":"3","reports_on_710":"2","last_report_text":"[1438147229] #Uruloki: arachnid nest mutewind purifiers"},{"name":"Arcade","band":"Redblade","dots":"2","reports_on_710":"1","last_report_text":"[1438148622] #Wilderness: Arcade - Redblade Raiders"},{"name":"Arena","band":"Brinerot","dots":"2","reports_on_710":"1","last_report_text":"[1438149818] #GreenLikeWhat: Arena Brinerot Pillagers"},{"name":"Arsenal","band":"Mutewind","dots":"1","reports_on_710":"1","last_report_text":"[1438147658] #Doedre_The_Hutt: arsenal mutewind trackers"},{"name":"Bazaar","band":"Mutewind","dots":"2","reports_on_710":"1","last_report_text":"[1438149540] #Shellfish: bazaar mutewind hunters"},{"name":"Colonnade","band":"Redblade","dots":"1","reports_on_710":"1","last_report_text":"[1438149065] #Uruloki: colonnade redblade scouts"},{"name":"Coves","band":"Redblade","dots":"2","reports_on_710":"2","last_report_text":"[1438148435] #RCGG: coves 72 - redblades raiders"},{"name":"Crypt","band":"Brinerot","dots":"2","reports_on_710":"1","last_report_text":"[1438148685] #Sibel_Can: Crypt Brinerot Pillager"},{"name":"Dark_Forest","band":"Brinerot","dots":"2","reports_on_710":"1","last_report_text":"[1438148446] #Friggs: Dark Forest Brinerot Pillagers"},{"name":"Desert","band":"Redblade","dots":"1","reports_on_710":"1","last_report_text":"[1438147958] #Flametotemkin: Desert Redblade Scouts"},{"name":"Dry_Woods","band":"Mutewind","dots":"2","reports_on_710":"1","last_report_text":"[1438149932] #SciscoCrash: Dry Woods Mutewind Hunters"},{"name":"Dungeon","band":"Mutewind","dots":"3","reports_on_710":"1","last_report_text":"[1438148481] #ArcheyNecro: dungeon 68 - mutewind purifiers"},{"name":"Excavation","band":"Brinerot","dots":"4","reports_on_710":"1","last_report_text":"[1438147574] #Brukhalian: excavation captured by the brinerot"},{"name":"Ghetto","band":"Brinerot","dots":"3","reports_on_710":"1","last_report_text":"[1438149222] #Sibel_Can: Ghetto Brinerot Buccaneers"},{"name":"Gorge","band":"Brinerot","dots":"1","reports_on_710":"1","last_report_text":"[1438147338] #RippingIsBanned: Gorge Brinerot Lookouts"},{"name":"Graveyard","band":"Mutewind","dots":"1","reports_on_710":"1","last_report_text":"[1438148813] #GreenLikeWhat: graveyard mutewind trackers"},{"name":"Grotto","band":"Brinerot","dots":"1","reports_on_710":"1","last_report_text":"[1438147950] #hereicome: grotto brinerot lockouts"},{"name":"Maelstrom_of_Chaos","band":"Mutewind","dots":"1","reports_on_710":"2","last_report_text":"[1438150655] #LeszczuTheSlayer: maelstrom of chaos mutewind trackers"},{"name":"Mine","band":"Brinerot","dots":"3","reports_on_710":"1","last_report_text":"[1438150262] #WhisperingDream: mine brinerot buccaneers"},{"name":"Mountain_Ledge","band":"Mutewind","dots":"2","reports_on_710":"2","last_report_text":"[1438149251] #MaruAtziri: mountain ledge mutewind hunters"},{"name":"Mud_Geyser","band":"Redblade","dots":"3","reports_on_710":"1","last_report_text":"[1438147509] #Reaving_Ranger: Mud Getser Redblade Fanatics"},{"name":"Necropolis","band":"Mutewind","dots":"1","reports_on_710":"1","last_report_text":"[1438150134] #Supine: necropolis mutewind trackers"},{"name":"Orchard","band":"Brinerot","dots":"2","reports_on_710":"1","last_report_text":"[1438148936] #WhisperingDream: orchard brinerot pillagers"},{"name":"Overgrown_Shrine","band":"Mutewind","dots":"2","reports_on_710":"1","last_report_text":"[1438150091] #ArcheyNecro: overgrown shrine 71 - mutewind hunters"},{"name":"Pier","band":"Mutewind","dots":"1","reports_on_710":"1","last_report_text":"[1438148670] #SciscoCrash: Pier Mutewind Trackers"},{"name":"Plateau","band":"Redblade","dots":"3","reports_on_710":"1","last_report_text":"[1438149809] #Awakened_Pizza: plateau redblade fanatics"},{"name":"Sewer","band":"Brinerot","dots":"1","reports_on_710":"1","last_report_text":"[1438148397] #MaruAtziri: sewer brinerot lookouts"},{"name":"Shipyard","band":"Mutewind","dots":"4","reports_on_710":"1","last_report_text":"[1438148236] #Awakened_Pizza: shipyard cleansed by the mutewind"},{"name":"Shore","band":"Mutewind","dots":"2","reports_on_710":"1","last_report_text":"[1438150664] #ArcheyNecro: shore 71 - mutewind hunters"},{"name":"Spider_Forest","band":"Redblade","dots":"1","reports_on_710":"1","last_report_text":"[1438149255] #FireAndFlames: Spider forest scouts"},{"name":"Springs","band":"Mutewind","dots":"2","reports_on_710":"1","last_report_text":"[1438148210] #DivinationCardCollector: springs mutewind hunters"},{"name":"Thicket","band":"Brinerot","dots":"2","reports_on_710":"1","last_report_text":"[1438149817] #ArcheyNecro: thicket 69 - brinerot pillagers"},{"name":"Torture_Chamber","band":"Redblade","dots":"2","reports_on_710":"3","last_report_text":"[1438149645] #RIPmyCastingAnimation:  Torture Chamber redblade raiders"},{"name":"Tropical_Island","band":"Redblade","dots":"1","reports_on_710":"2","last_report_text":"[1438150277] #MaruAtziri: tropical island redblade scouts"},{"name":"Vaal_Pyramid","band":"Redblade","dots":"1","reports_on_710":"1","last_report_text":"[1438148783] #Shower: Vaal pyramid redblade scouts"},{"name":"Vaults_of_Atziri","band":"Brinerot","dots":"3","reports_on_710":"1","last_report_text":"[1438147268] #Superman: vaults of atziri brinetor buccaneers"},{"name":"Wharf","band":"Redblade","dots":"2","reports_on_710":"1","last_report_text":"[1438147464] #Sibel_Can: Wharf Redblade Raiders"}],"timeslot":399485}