{"maps":[{"name":"Arachnid_Nest","band":"Brinerot","dots":"3","reports_on_710":"1","last_report_text":"[0] #Dev: No message"},{"name":"Canyon","band":"Brinerot","dots":"2","reports_on_710":"1","last_report_text":"[0] #Dev: No message"},{"name":"Courtyard","band":"Redblade","dots":"1","reports_on_710":"1","last_report_text":"[0] #Dev: No message"},{"name":"Crematorium","band":"Mutewind","dots":"2","reports_on_710":"1","last_report_text":"[0] #Dev: No message"},{"name":"Dry_Peninsula","band":"Brinerot","dots":"3","reports_on_710":"1","last_report_text":"[0] #Dev: No message"},{"name":"Dry_Woods","band":"Brinerot","dots":"1","reports_on_710":"1","last_report_text":"[0] #Dev: No message"},{"name":"Jungle_Valley","band":"Brinerot","dots":"1","reports_on_710":"1","last_report_text":"[0] #Dev: No message"},{"name":"Residence","band":"Redblade","dots":"1","reports_on_710":"1","last_report_text":"[0] #Dev: No message"},{"name":"Spider_Lair","band":"Mutewind","dots":"3","reports_on_710":"1","last_report_text":"[0] #Dev: No message"},{"name":"Temple","band":"Mutewind","dots":"4","reports_on_710":"2","last_report_text":"[0] #Dev: No message"},{"name":"Torture_Chamber","band":"Mutewind","dots":"3","reports_on_710":"1","last_report_text":"[0] #Dev: No message"},{"name":"Tropical_Island","band":"Mutewind","dots":"1","reports_on_710":"1","last_report_text":"[0] #Dev: No message"},{"name":"Underground_Sea","band":"Mutewind","dots":"1","reports_on_710":"1","last_report_text":"[0] #Dev: No message"}],"timeslot":399362}