{"maps":[{"name":"Academy","band":"Mutewind","dots":"2","reports_on_710":"2","last_report_text":"[1437960440] #Haudruff: Academy Mutewind Hunter"},{"name":"Arcade","band":"Mutewind","dots":"2","reports_on_710":"2","last_report_text":"[1437961410] #Kroyid: arcade has Mutewind Hunter"},{"name":"Arena","band":"Mutewind","dots":"2","reports_on_710":"2","last_report_text":"[1437961780] #TwistingClaw: arena mutewind hunter"},{"name":"Channel","band":"Mutewind","dots":"1","reports_on_710":"2","last_report_text":"[1437960886] #Vyzzi: Channel - Mutewind Tracker"},{"name":"Colonnade","band":"Redblade","dots":"1","reports_on_710":"2","last_report_text":"[1437961090] #lelbois: Colonnade redblade scout"},{"name":"Coves","band":"Mutewind","dots":"1","reports_on_710":"2","last_report_text":"[1437961710] #Angora: coves tracker"},{"name":"Dark_Forest","band":"Mutewind","dots":"1","reports_on_710":"2","last_report_text":"[1437961728] #thundercougarfalconbird: Dark Forest Mutewind Tracker"},{"name":"Desert","band":"Mutewind","dots":"1","reports_on_710":"3","last_report_text":"[1437962206] #Reaving_Ranger: Desert Mutewind Tracker"},{"name":"Dry_Peninsula","band":"Brinerot","dots":"1","reports_on_710":"2","last_report_text":"[1437961270] #Haudruff: Dry Peninsula Brinerot Lookout"},{"name":"Dry_Woods","band":"Brinerot","dots":"1","reports_on_710":"2","last_report_text":"[1437961308] #SummonTimeBitch: dry woods brinerot lookout"},{"name":"Dungeon","band":"Mutewind","dots":"3","reports_on_710":"1","last_report_text":"[1437960377] #EleRng: dungeon Mutewind Purifier"},{"name":"Ghetto","band":"Redblade","dots":"1","reports_on_710":"3","last_report_text":"[1437963622] #Reaving_Ranger: Ghetto Redblade Scout"},{"name":"Graveyard","band":"Brinerot","dots":"2","reports_on_710":"2","last_report_text":"[1437962859] #bbotx: graveyard brinerot pillager"},{"name":"Grotto","band":"Mutewind","dots":"1","reports_on_710":"1","last_report_text":"[1437960374] #Pezant_SRS: Grotto Mutewind Tracker"},{"name":"Jungle_Valley","band":"Mutewind","dots":"1","reports_on_710":"2","last_report_text":"[1437963207] #Angora: jungle valley tracker"},{"name":"Labyrinth","band":"Redblade","dots":"2","reports_on_710":"2","last_report_text":"[1437963045] #Yavispin: labyrinth redblade raider"},{"name":"Maze","band":"Brinerot","dots":"4","reports_on_710":"2","last_report_text":"[1437963199] #supportbuildorsomething: maze captured by the brinero"},{"name":"Mountain_Ledge","band":"Mutewind","dots":"2","reports_on_710":"10","last_report_text":"[1437963577] #WhirlingFinder: mountain ledge mutewind hunter"},{"name":"Mud_Geyser","band":"Redblade","dots":"1","reports_on_710":"2","last_report_text":"[1437961053] #Synair: Mud Geyser redblade scout"},{"name":"Necropolis","band":"Mutewind","dots":"2","reports_on_710":"1","last_report_text":"[1437961893] #EleRng: Necropolis Mutewind Hunte"},{"name":"Oba's_Cursed_Trove","band":"Brinerot","dots":"4","reports_on_710":"1","last_report_text":"[1437962413] #Squid: oba's cursed trove captured by the brinero"},{"name":"Orchard","band":"Redblade","dots":"3","reports_on_710":"2","last_report_text":"[1437961441] #Elmiii:  Orchard Redblade Fanatic"},{"name":"Overgrown_Shrine","band":"Brinerot","dots":"2","reports_on_710":"2","last_report_text":"[1437962884] #Haudruff: Overgrown Shrine Brinerot Pillager"},{"name":"Promenade","band":"Redblade","dots":"2","reports_on_710":"6","last_report_text":"[1437961324] #Shilasse: promenade redblade raider"},{"name":"Residence","band":"Brinerot","dots":"2","reports_on_710":"2","last_report_text":"[1437960314] #Friggs: Residence brinerot pillager"},{"name":"Sewer","band":"Redblade","dots":"2","reports_on_710":"2","last_report_text":"[1437960946] #kalzonwar: sewer redblade raiders"},{"name":"Spider_Forest","band":"Mutewind","dots":"2","reports_on_710":"2","last_report_text":"[1437960855] #Alicha:  Spider Forest Mutewind Hunter"},{"name":"Spider_Lair","band":"Mutewind","dots":"1","reports_on_710":"1","last_report_text":"[1437962324] #Kroyid: spider lair > mutewind tracker"},{"name":"Strand","band":"Brinerot","dots":"2","reports_on_710":"6","last_report_text":"[1437963228] #RIP_Stannis_Baratheon: strand pillager"},{"name":"The_Apex_of_Sacrifice","band":"Brinerot","dots":"1","reports_on_710":"2","last_report_text":"[1437960481] #Suddenly: the apex of sacrifice brinerot lookout"},{"name":"Tunnel","band":"Brinerot","dots":"3","reports_on_710":"2","last_report_text":"[1437962575] #Meriannelle: tunnel = brinerot buccaneer"},{"name":"Underground_Sea","band":"Mutewind","dots":"1","reports_on_710":"1","last_report_text":"[1437962163] #Vyzzi: Underground Sea - Mutewind Tracker"},{"name":"Vaal_Pyramid","band":"Brinerot","dots":"2","reports_on_710":"2","last_report_text":"[1437960684] #Pengupoison: Vaal Pyramid Brinerot Pillager"},{"name":"Villa","band":"Redblade","dots":"3","reports_on_710":"6","last_report_text":"[1437963764] #ssssssssssssssssssssss: villa is redblade fanatic"},{"name":"Volcano","band":"Redblade","dots":"1","reports_on_710":"2","last_report_text":"[1437960440] #Kainenn: Redblade Scouts Volcan"},{"name":"Waste_Pool","band":"Brinerot","dots":"1","reports_on_710":"2","last_report_text":"[1437961272] #GreaseInMyEyes: waste pool brine lookout"},{"name":"Waterways","band":"Mutewind","dots":"4","reports_on_710":"2","last_report_text":"[1437960818] #SanicTehHadgeHoog: waterways cleansed by the mutewin"}],"timeslot":399433}