{"maps":[{"name":"Arcade","band":"Redblade","dots":"2","reports_on_710":"1","last_report_text":"[1438169911] #Uncouth: arcade raiders"},{"name":"Arena","band":"Brinerot","dots":"4","reports_on_710":"2","last_report_text":"[1438170924] #ukigoboom: arena captured by brinerot"},{"name":"Arid_Lake","band":"Brinerot","dots":"1","reports_on_710":"1","last_report_text":"[1438171746] #THEBIGBLACKSPINNER: arid lake lookouts"},{"name":"Arsenal","band":"Mutewind","dots":"1","reports_on_710":"1","last_report_text":"[1438172217] #TheTouchOfDoge: arsenal m1"},{"name":"Canyon","band":"Brinerot","dots":"2","reports_on_710":"1","last_report_text":"[1438170398] #BiberKaomsMoM: Canyon Brinerot Pillagers"},{"name":"Crypt","band":"Brinerot","dots":"2","reports_on_710":"1","last_report_text":"[1438169091] #DukeEpiel: Crypt birnroot pillagers"},{"name":"Dry_Woods","band":"Mutewind","dots":"2","reports_on_710":"1","last_report_text":"[1438170003] #Loppa_Witch: dry woods mutewind hunters"},{"name":"Dungeon","band":"Brinerot","dots":"1","reports_on_710":"1","last_report_text":"[1438171856] #JeSuisBoom: dungeon brineroot lookouts"},{"name":"Ghetto","band":"Brinerot","dots":"4","reports_on_710":"1","last_report_text":"[1438170129] #FlamingHotPocket: ghetto - captured by brinerot"},{"name":"Grotto","band":"Brinerot","dots":"2","reports_on_710":"1","last_report_text":"[1438170281] #Irvinoulina: grotto binerot pillagers"},{"name":"Jungle_Valley","band":"Mutewind","dots":"1","reports_on_710":"2","last_report_text":"[1438170424] #JeSuisBoom: Jungle valley trackers"},{"name":"Mud_Geyser","band":"Redblade","dots":"1","reports_on_710":"1","last_report_text":"[1438169205] #FlamingHotPocket: mud geyser - redblade scouts"},{"name":"Museum","band":"Redblade","dots":"1","reports_on_710":"1","last_report_text":"[1438170763] #BallsToTheVaal: Museum Redblade Scouts"},{"name":"Pit","band":"Redblade","dots":"1","reports_on_710":"1","last_report_text":"[1438169188] #Uncouth: pit scouts"},{"name":"Quarry","band":"Redblade","dots":"1","reports_on_710":"1","last_report_text":"[1438169019] #Hellbringer: quarry scouts"},{"name":"Reef","band":"Mutewind","dots":"4","reports_on_710":"1","last_report_text":"[1438169038] #BallsToTheVaal: Reef Cleansed by Mutewind"},{"name":"Residence","band":"Mutewind","dots":"2","reports_on_710":"1","last_report_text":"[1438170983] #THEBIGBLACKSPINNER: residence mutewind hunters"},{"name":"Sewer","band":"Brinerot","dots":"3","reports_on_710":"1","last_report_text":"[1438170915] #Duchess_Sterling: sewer brinerot buccaneers"},{"name":"Shipyard","band":"Brinerot","dots":"4","reports_on_710":"1","last_report_text":"[1438172216] #Avicinerate: Shipyard (Zana) captured by the Brinerot"},{"name":"Shore","band":"Mutewind","dots":"4","reports_on_710":"3","last_report_text":"[1438171085] #ukigoboom: shore cleansed by the mutewind"},{"name":"Springs","band":"Mutewind","dots":"4","reports_on_710":"1","last_report_text":"[1438169593] #ToolAenima: springs cleansed by mutewind"},{"name":"Vaal_Pyramid","band":"Redblade","dots":"2","reports_on_710":"1","last_report_text":"[1438169266] #FauxFlames: Vaal Pyramid: Redblade Raiders"},{"name":"Villa","band":"Mutewind","dots":"2","reports_on_710":"1","last_report_text":"[1438169197] #Burningbum: villa - mutewind hunters"},{"name":"Waste_Pool","band":"Brinerot","dots":"3","reports_on_710":"3","last_report_text":"[1438171893] #ShesAKillerQueeeen: Waste pool buccaneers"},{"name":"Wharf","band":"Redblade","dots":"2","reports_on_710":"1","last_report_text":"[1438171842] #Duchess_Sterling: wharf redblade raiders"}],"timeslot":399491}